stuffpages/__init__.py
stuffpages/__main__.py
stuffpages/__meta__.py
stuffpages/_stuffpages.py
stuffpages/_stuffpages/config.py
stuffpages/_stuffpages/styles/default-dark.css
stuffpages/_stuffpages/styles/default.css
stuffpages/_stuffpages/styles/selenized-black.css
stuffpages/_stuffpages/styles/selenized-dark.css
stuffpages/_stuffpages/styles/selenized-light.css
stuffpages/_stuffpages/styles/selenized-white.css
stuffpages/_stuffpages/styles/simple.css
StuffPages-0.7.4.dist-info/METADATA
StuffPages-0.7.4.dist-info/WHEEL
StuffPages-0.7.4.dist-info/entry_points.txt
StuffPages-0.7.4.dist-info/top_level.txt
StuffPages-0.7.4.dist-info/RECORD
