Metadata-Version: 2.1
Name: StuffPages
Version: 0.7.4
Summary: StuffPages - A quick way to create simple web pages using Markdown
Home-page: https://fladd.github.io/StuffPages/
Author: Florian Krause
Author-email: florian.krause@fladd.de
Classifier: Programming Language :: Python :: 3
Classifier: License :: OSI Approved :: MIT License
Classifier: Operating System :: OS Independent
Requires-Python: >=3.6
Requires-Dist: markdown (==3.3.7)
Requires-Dist: pymdown-extensions (==9.5)
Requires-Dist: Pygments (==2.12.0)
Requires-Dist: beautifulsoup4 (==4.11.1)
